appinventor/__init__.py
appinventor/tfjs/__init__.py
appinventor/tfjs/__main__.py
appinventor/tfjs/template/TensorflowTemplate.java
appinventor/tfjs/template/assets/app.js
appinventor/tfjs/template/assets/index.html
appinventor_tfjs-0.1.4.dist-info/LICENSE
appinventor_tfjs-0.1.4.dist-info/METADATA
appinventor_tfjs-0.1.4.dist-info/WHEEL
appinventor_tfjs-0.1.4.dist-info/entry_points.txt
appinventor_tfjs-0.1.4.dist-info/top_level.txt
appinventor_tfjs-0.1.4.dist-info/RECORD
