Metadata-Version: 2.1
Name: appinventor-tfjs
Version: 0.1.4
Summary: Tool for generating App Inventor extension skeletons from Tensorflow.js models
Home-page: https://github.com/mit-cml/tfjs-extension-tool
Author: Evan W. Patton
Author-email: ewpatton@mit.edu
License: Apache
Platform: UNKNOWN
Classifier: Development Status :: 3 - Alpha
Classifier: Environment :: Console
Classifier: License :: OSI Approved :: Apache Software License
Classifier: Natural Language :: English
Classifier: Operating System :: OS Independent
Classifier: Programming Language :: JavaScript
Classifier: Programming Language :: Python :: 3
Classifier: Topic :: Education
Classifier: Topic :: Scientific/Engineering :: Artificial Intelligence
Classifier: Topic :: Software Development
Classifier: Topic :: Software Development :: Code Generators
Requires-Python: >=3.0
Requires-Dist: certifi
